{"width": 16, "height": 16, "background": "transparent", "grid_lines": false, "pixel_size": 1, "pixels": [{"x": 5, "y": 2, "color": "#E5484D"}, {"x": 6, "y": 2, "color": "#E5484D"}, {"x": 7, "y": 2, "color": "#E5484D"}, {"x": 8, "y": 2, "color": "#E5484D"}, {"x": 4, "y": 3, "color": "#E5484D"}, {"x": 5, "y": 3, "color": "#E5484D"}, {"x": 6, "y": 3, "color": "#0B1322"}, {"x": 7, "y": 3, "color": "#0B1322"}, {"x": 8, "y": 3, "color": "#0B1322"}, {"x": 9, "y": 3, "color": "#0B1322"}, {"x": 3, "y": 4, "color": "#E5484D"}, {"x": 4, "y": 4, "color": "#E5484D"}, {"x": 5, "y": 4, "color": "#0B1322"}, {"x": 6, "y": 4, "color": "#0B1322"}, {"x": 3, "y": 5, "color": "#E5484D"}, {"x": 4, "y": 5, "color": "#E5484D"}, {"x": 5, "y": 5, "color": "#0B1322"}, {"x": 3, "y": 6, "color": "#E5484D"}, {"x": 4, "y": 6, "color": "#E5484D"}, {"x": 5, "y": 6, "color": "#E5484D"}, {"x": 6, "y": 6, "color": "#E5484D"}, {"x": 7, "y": 6, "color": "#E5484D"}, {"x": 8, "y": 6, "color": "#E5484D"}, {"x": 3, "y": 7, "color": "#E5484D"}, {"x": 4, "y": 7, "color": "#E5484D"}, {"x": 5, "y": 7, "color": "#E5484D"}, {"x": 6, "y": 7, "color": "#0B1322"}, {"x": 7, "y": 7, "color": "#0B1322"}, {"x": 8, "y": 7, "color": "#E5484D"}, {"x": 9, "y": 7, "color": "#E5484D"}, {"x": 3, "y": 8, "color": "#E5484D"}, {"x": 4, "y": 8, "color": "#E5484D"}, {"x": 5, "y": 8, "color": "#0B1322"}, {"x": 6, "y": 8, "color": "#0B1322"}, {"x": 8, "y": 8, "color": "#E5484D"}, {"x": 9, "y": 8, "color": "#E5484D"}, {"x": 10, "y": 8, "color": "#0B1322"}, {"x": 3, "y": 9, "color": "#E5484D"}, {"x": 4, "y": 9, "color": "#E5484D"}, {"x": 5, "y": 9, "color": "#0B1322"}, {"x": 8, "y": 9, "color": "#E5484D"}, {"x": 9, "y": 9, "color": "#E5484D"}, {"x": 10, "y": 9, "color": "#0B1322"}, {"x": 3, "y": 10, "color": "#E5484D"}, {"x": 4, "y": 10, "color": "#E5484D"}, {"x": 5, "y": 10, "color": "#0B1322"}, {"x": 8, "y": 10, "color": "#E5484D"}, {"x": 9, "y": 10, "color": "#E5484D"}, {"x": 10, "y": 10, "color": "#0B1322"}, {"x": 3, "y": 11, "color": "#E5484D"}, {"x": 4, "y": 11, "color": "#E5484D"}, {"x": 5, "y": 11, "color": "#0B1322"}, {"x": 8, "y": 11, "color": "#E5484D"}, {"x": 9, "y": 11, "color": "#E5484D"}, {"x": 10, "y": 11, "color": "#0B1322"}, {"x": 4, "y": 12, "color": "#E5484D"}, {"x": 5, "y": 12, "color": "#E5484D"}, {"x": 6, "y": 12, "color": "#E5484D"}, {"x": 7, "y": 12, "color": "#E5484D"}, {"x": 8, "y": 12, "color": "#E5484D"}, {"x": 9, "y": 12, "color": "#0B1322"}, {"x": 10, "y": 12, "color": "#0B1322"}, {"x": 4, "y": 13, "color": "#E5484D"}, {"x": 5, "y": 13, "color": "#E5484D"}, {"x": 6, "y": 13, "color": "#E5484D"}, {"x": 7, "y": 13, "color": "#E5484D"}, {"x": 8, "y": 13, "color": "#E5484D"}, {"x": 9, "y": 13, "color": "#0B1322"}, {"x": 5, "y": 14, "color": "#0B1322"}, {"x": 6, "y": 14, "color": "#0B1322"}, {"x": 7, "y": 14, "color": "#0B1322"}, {"x": 8, "y": 14, "color": "#0B1322"}, {"x": 9, "y": 14, "color": "#0B1322"}]}